MANIFEST.in
README.md
setup.py
django_stdnumfield.egg-info/PKG-INFO
django_stdnumfield.egg-info/SOURCES.txt
django_stdnumfield.egg-info/dependency_links.txt
django_stdnumfield.egg-info/requires.txt
django_stdnumfield.egg-info/top_level.txt
stdnumfield/__init__.py
stdnumfield/_formats.py
stdnumfield/apps.py
stdnumfield/forms.py
stdnumfield/models.py
stdnumfield/settings.py
stdnumfield/utils.py
stdnumfield/validators.py